{
  "type": "Feature",
  "properties": {
    "gn:admin1_code":"03",
    "gn:asciiname":"Mangia",
    "gn:country_code":"TO",
    "gn:dem":20,
    "gn:feature_class":"P",
    "gn:feature_code":"PPL",
    "gn:name":"Mangia",
    "gn:population":0,
    "gn:timezone":"Pacific/Tongatapu",
    "iso:country":"TO",
    "wof:name":"Mangia",
    "wof:placetype":"locality"
},
  "geometry": {"coordinates":[-173.95616000000001,-18.62524],"type":"Point"}
}