{
  "type": "Feature",
  "properties": {
    "gn:admin1_code":"02",
    "gn:asciiname":"Utulau",
    "gn:country_code":"TO",
    "gn:dem":23,
    "gn:feature_class":"P",
    "gn:feature_code":"PPL",
    "gn:name":"Utulau",
    "gn:population":0,
    "gn:timezone":"Pacific/Tongatapu",
    "iso:country":"TO",
    "name:ton_x_preferred":[
        "Utulau"
    ],
    "name:und_x_variant":[
        "\u2018Utulau"
    ],
    "wof:name":"Utulau",
    "wof:placetype":"locality"
},
  "geometry": {"coordinates":[-175.26667,-21.18333],"type":"Point"}
}