{
  "type": "Feature",
  "properties": {
    "gn:admin1_code":"02",
    "gn:asciiname":"Houma",
    "gn:country_code":"TO",
    "gn:dem":24,
    "gn:feature_class":"P",
    "gn:feature_code":"PPL",
    "gn:name":"Houma",
    "gn:population":0,
    "gn:timezone":"Pacific/Tongatapu",
    "iso:country":"TO",
    "name:pol_x_preferred":[
        "Houma"
    ],
    "name:ton_x_preferred":[
        "Houma"
    ],
    "wof:name":"Houma",
    "wof:placetype":"locality"
},
  "geometry": {"coordinates":[-175.30213000000001,-21.17005],"type":"Point"}
}