{
  "type": "Feature",
  "properties": {
    "gn:admin1_code":"02",
    "gn:asciiname":"Houma",
    "gn:country_code":"TO",
    "gn:dem":24,
    "gn:feature_class":"P",
    "gn:feature_code":"PPL",
    "gn:name":"Houma",
    "gn:population":0,
    "gn:timezone":"Pacific/Tongatapu",
    "iso:country":"TO",
    "name:ben_x_preferred":[
        "\u09b9\u09cc\u09ae\u09be"
    ],
    "name:ell_x_preferred":[
        "\u03a7\u03bf\u03cd\u03bc\u03b1"
    ],
    "name:fas_x_preferred":[
        "\u0647\u0648\u0645\u0627"
    ],
    "name:heb_x_preferred":[
        "\u05d7\u05d5\u05de\u05d4"
    ],
    "name:hin_x_preferred":[
        "\u0939\u0942\u092e\u093e"
    ],
    "name:hun_x_preferred":[
        "Houma"
    ],
    "name:ind_x_preferred":[
        "Houma"
    ],
    "name:pol_x_preferred":[
        "Houma"
    ],
    "name:por_x_preferred":[
        "Houma"
    ],
    "name:rus_x_preferred":[
        "\u0425\u0443\u043c\u0430"
    ],
    "name:spa_x_preferred":[
        "Houma"
    ],
    "name:ton_x_preferred":[
        "Houma"
    ],
    "name:vie_x_preferred":[
        "Houma"
    ],
    "wof:name":"Houma",
    "wof:placetype":"locality"
},
  "geometry": {"coordinates":[-175.30213000000001,-21.17005],"type":"Point"}
}