{
  "type": "Feature",
  "properties": {
    "gn:asciiname":"Matangiake",
    "gn:country_code":"TO",
    "gn:dem":11,
    "gn:feature_class":"P",
    "gn:feature_code":"PPLL",
    "gn:name":"Matangiake",
    "gn:population":0,
    "gn:timezone":"Pacific/Tongatapu",
    "iso:country":"TO",
    "wof:name":"Matangiake",
    "wof:placetype":"locality"
},
  "geometry": {"coordinates":[-175.27626999999995,-21.16468],"type":"Point"}
}