{
  "type": "Feature",
  "properties": {
    "gn:admin1_code":"02",
    "gn:asciiname":"Ha`utu",
    "gn:country_code":"TO",
    "gn:dem":20,
    "gn:feature_class":"P",
    "gn:feature_code":"PPL",
    "gn:name":"H\u0101\u2018utu",
    "gn:population":0,
    "gn:timezone":"Pacific/Tongatapu",
    "iso:country":"TO",
    "name:ton_x_preferred":[
        "H\u0101\u2018utu"
    ],
    "name:ton_x_variant":[
        "Ha\u2018utu"
    ],
    "wof:name":"Ha`utu",
    "wof:placetype":"locality"
},
  "geometry": {"coordinates":[-175.32983999999999,-21.14459],"type":"Point"}
}