{
  "type": "Feature",
  "properties": {
    "gn:admin1_code":"02",
    "gn:asciiname":"Te`ekiu",
    "gn:country_code":"TO",
    "gn:dem":8,
    "gn:feature_class":"P",
    "gn:feature_code":"PPL",
    "gn:name":"Te\u2018ekiu",
    "gn:population":0,
    "gn:timezone":"Pacific/Tongatapu",
    "iso:country":"TO",
    "wof:name":"Te`ekiu",
    "wof:placetype":"locality"
},
  "geometry": {"coordinates":[-175.31868,-21.12822],"type":"Point"}
}