{
  "type": "Feature",
  "properties": {
    "gn:admin1_code":"03",
    "gn:asciiname":"Koloa",
    "gn:country_code":"TO",
    "gn:dem":1,
    "gn:feature_class":"P",
    "gn:feature_code":"PPL",
    "gn:name":"Koloa",
    "gn:population":0,
    "gn:timezone":"Pacific/Tongatapu",
    "iso:country":"TO",
    "wof:name":"Koloa",
    "wof:placetype":"locality"
},
  "geometry": {"coordinates":[-173.93672000000001,-18.64599],"type":"Point"}
}