{
  "type": "Feature",
  "properties": {
    "gn:admin1_code":"03",
    "gn:asciiname":"Holeva",
    "gn:country_code":"TO",
    "gn:dem":9,
    "gn:feature_class":"P",
    "gn:feature_code":"PPL",
    "gn:name":"Holeva",
    "gn:population":0,
    "gn:timezone":"Pacific/Tongatapu",
    "iso:country":"TO",
    "wof:name":"Holeva",
    "wof:placetype":"locality"
},
  "geometry": {"coordinates":[-173.92205000000001,-18.64246],"type":"Point"}
}