{
  "type": "Feature",
  "properties": {
    "gn:admin1_code":"02",
    "gn:asciiname":"Ha`akame",
    "gn:country_code":"TO",
    "gn:dem":29,
    "gn:feature_class":"P",
    "gn:feature_code":"PPL",
    "gn:name":"Ha\u2018akame",
    "gn:population":0,
    "gn:timezone":"Pacific/Tongatapu",
    "iso:country":"TO",
    "wof:name":"Ha`akame",
    "wof:placetype":"locality"
},
  "geometry": {"coordinates":[-175.28491,-21.18288],"type":"Point"}
}