{
  "type": "Feature",
  "properties": {
    "gn:admin1_code":"03",
    "gn:asciiname":"Makave",
    "gn:country_code":"TO",
    "gn:dem":14,
    "gn:feature_class":"P",
    "gn:feature_code":"PPL",
    "gn:name":"Makave",
    "gn:population":0,
    "gn:timezone":"Pacific/Tongatapu",
    "iso:country":"TO",
    "wof:name":"Makave",
    "wof:placetype":"locality"
},
  "geometry": {"coordinates":[-173.96566999999999,-18.65194],"type":"Point"}
}