{
  "type": "Feature",
  "properties": {
    "gn:asciiname":"Okoa",
    "gn:country_code":"TO",
    "gn:dem":11,
    "gn:feature_class":"P",
    "gn:feature_code":"PPL",
    "gn:name":"Okoa",
    "gn:population":0,
    "gn:timezone":"Pacific/Tongatapu",
    "iso:country":"TO",
    "name:und_x_variant":[
        "'Okoa"
    ],
    "wof:name":"Okoa",
    "wof:placetype":"locality"
},
  "geometry": {"coordinates":[-173.95313999999999,-18.64864],"type":"Point"}
}