{
  "type": "Feature",
  "properties": {
    "gn:admin1_code":"03",
    "gn:asciiname":"Luahoko",
    "gn:country_code":"TO",
    "gn:dem":-9999,
    "gn:feature_class":"P",
    "gn:feature_code":"PPL",
    "gn:name":"Luahoko",
    "gn:population":0,
    "gn:timezone":"Pacific/Tongatapu",
    "iso:country":"TO",
    "name:ton_x_preferred":[
        "Luahoko"
    ],
    "wof:name":"Luahoko",
    "wof:placetype":"locality"
},
  "geometry": {"coordinates":[-174.39229,-19.67198],"type":"Point"}
}