{
  "type": "Feature",
  "properties": {
    "gn:admin1_code":"01",
    "gn:asciiname":"Muitoa",
    "gn:country_code":"TO",
    "gn:dem":10,
    "gn:feature_class":"P",
    "gn:feature_code":"PPL",
    "gn:name":"Muitoa",
    "gn:population":0,
    "gn:timezone":"Pacific/Tongatapu",
    "iso:country":"TO",
    "wof:name":"Muitoa",
    "wof:placetype":"locality"
},
  "geometry": {"coordinates":[-174.29441,-19.65229],"type":"Point"}
}