{
  "type": "Feature",
  "properties": {
    "gn:admin1_code":"02",
    "gn:asciiname":"Alaki",
    "gn:country_code":"TO",
    "gn:dem":11,
    "gn:feature_class":"P",
    "gn:feature_code":"PPL",
    "gn:name":"Alaki",
    "gn:population":0,
    "gn:timezone":"Pacific/Tongatapu",
    "iso:country":"TO",
    "wof:name":"Alaki",
    "wof:placetype":"locality"
},
  "geometry": {"coordinates":[-175.13158000000001,-21.19282],"type":"Point"}
}