{
  "type": "Feature",
  "properties": {
    "gn:admin1_code":"01",
    "gn:asciiname":"Koulo",
    "gn:country_code":"TO",
    "gn:dem":8,
    "gn:feature_class":"P",
    "gn:feature_code":"PPL",
    "gn:name":"Koulo",
    "gn:population":0,
    "gn:timezone":"Pacific/Tongatapu",
    "iso:country":"TO",
    "wof:name":"Koulo",
    "wof:placetype":"locality"
},
  "geometry": {"coordinates":[-174.34486999999999,-19.78835],"type":"Point"}
}