{
  "type": "Feature",
  "properties": {
    "gn:admin1_code":"03",
    "gn:asciiname":"Mu`a",
    "gn:country_code":"TO",
    "gn:dem":51,
    "gn:feature_class":"P",
    "gn:feature_code":"PPL",
    "gn:name":"Mu\u2018a",
    "gn:population":0,
    "gn:timezone":"Pacific/Tongatapu",
    "iso:country":"TO",
    "wof:name":"Mu`a",
    "wof:placetype":"locality"
},
  "geometry": {"coordinates":[-175.60478000000001,-15.59741],"type":"Point"}
}