{
  "type": "Feature",
  "properties": {
    "gn:admin1_code":"03",
    "gn:asciiname":"Kapa",
    "gn:country_code":"TO",
    "gn:dem":20,
    "gn:feature_class":"P",
    "gn:feature_code":"PPL",
    "gn:name":"Kapa",
    "gn:population":0,
    "gn:timezone":"Pacific/Tongatapu",
    "iso:country":"TO",
    "wof:name":"Kapa",
    "wof:placetype":"locality"
},
  "geometry": {"coordinates":[-174.03663999999995,-18.70705],"type":"Point"}
}