{
  "type": "Feature",
  "properties": {
    "gn:admin1_code":"03",
    "gn:asciiname":"Tefisi",
    "gn:country_code":"TO",
    "gn:dem":94,
    "gn:feature_class":"P",
    "gn:feature_code":"PPL",
    "gn:name":"Tefisi",
    "gn:population":0,
    "gn:timezone":"Pacific/Tongatapu",
    "iso:country":"TO",
    "name:und_x_variant":[
        "Ngaakau",
        "Tefisi"
    ],
    "wof:name":"Tefisi",
    "wof:placetype":"locality"
},
  "geometry": {"coordinates":[-174.01447999999999,-18.62976],"type":"Point"}
}